tests/__init__.py
tests/conftest.py
tests/test_methods.py
tests/test_sess.py
vkinfo/__init__.py
vkinfo/__main__.py
vkinfo/config.py
vkinfo/exceptions.py
vkinfo/get_token.py
vkinfo/vk_api.py
vkinfo/util/__init__.py
vkinfo/util/export.py
vkinfo/util/parsers.py
vkinfo-0.1.1.dist-info/LICENSE.txt
vkinfo-0.1.1.dist-info/METADATA
vkinfo-0.1.1.dist-info/WHEEL
vkinfo-0.1.1.dist-info/entry_points.txt
vkinfo-0.1.1.dist-info/top_level.txt
vkinfo-0.1.1.dist-info/RECORD
