Metadata-Version: 2.1
Name: vkinfo
Version: 0.1.1
Summary: VK users data analyzer
Home-page: https://github.com/Addic7edBoy/ImprovadoTest
Author: Max Medvedev
License: MIT
Platform: UNKNOWN
Classifier: Programming Language :: Python :: 3.8
Classifier: License :: OSI Approved :: MIT License
Classifier: Operating System :: Unix
Requires-Python: >=3.6
License-File: LICENSE.txt
Requires-Dist: requests
Requires-Dist: pandas
Requires-Dist: webbrowser
Requires-Dist: dotenv
Requires-Dist: httpretty
